coffee_price/__init__.py
coffee_price/admin.py
coffee_price/apps.py
coffee_price/models.py
coffee_price/tests.py
coffee_price/urls.py
coffee_price/views.py
coffee_price/api/__init__.py
coffee_price/api/serializers/__init__.py
coffee_price/api/serializers/price.py
coffee_price/api/services/__init__.py
coffee_price/api/services/coffee_price.py
coffee_price/lib/__init__.py
coffee_price/lib/managers/__init__.py
coffee_price/lib/managers/price.py
coffee_price/migrations/0001_initial.py
coffee_price/migrations/0002_alter_price_product.py
coffee_price/migrations/__init__.py
coffee_price/tasks/__init__.py
coffee_price/tasks/get_prices.py
django_oasis4_coffee_price-1.0.6.dist-info/LICENSE
django_oasis4_coffee_price-1.0.6.dist-info/METADATA
django_oasis4_coffee_price-1.0.6.dist-info/WHEEL
django_oasis4_coffee_price-1.0.6.dist-info/top_level.txt
django_oasis4_coffee_price-1.0.6.dist-info/RECORD
