Metadata-Version: 2.1
Name: django-oasis4-coffee-price
Version: 1.0.6
Summary: Cadefihuila Coffee Price REST Services
Author-email: Mario Cerón <mario.ceron@cqinversiones.co>
License: GNU GENERAL PUBLIC LICENSE
Keywords: django,cadefihuila
Classifier: License :: Other/Proprietary License
Classifier: Programming Language :: Python :: 3.9
Classifier: Development Status :: 5 - Production/Stable
Classifier: Framework :: Django
Classifier: Framework :: Django :: 4.1
Classifier: Environment :: Web Environment
Classifier: Operating System :: OS Independent
Classifier: Topic :: Internet :: WWW/HTTP
Requires-Python: >=3.9
License-File: LICENSE
Requires-Dist: Django (>=4.1)
Requires-Dist: djangorestframework
Requires-Dist: django-oasis4 (>=1.0.6)
Requires-Dist: zibanu-django
Requires-Dist: celery (>=5.2.7)
Requires-Dist: django-celery-beat
